Metadata-Version: 1.0
Name: AWS-PYPI-Practice
Version: 0.2
Summary: Gaussian distributions
Home-page: UNKNOWN
Author: Ao Wang
Author-email: aw3338@drexel.edu
License: UNKNOWN
Platform: UNKNOWN
